gluelib/__init__.py
gluelib-1.2.1.dist-info/LICENSE
gluelib-1.2.1.dist-info/METADATA
gluelib-1.2.1.dist-info/WHEEL
gluelib-1.2.1.dist-info/top_level.txt
gluelib-1.2.1.dist-info/RECORD
