Metadata-Version: 2.1
Name: gluelib
Version: 1.2.1
Summary: A simple library for the pastebin API
Home-page: https://github.com/hrjkknox/gluelib
Author: Hamish Knox
Author-email: hrjkknox@gmail.com
License: UNKNOWN
Project-URL: Bug Tracker, https://github.com/hrjkknox/gluelib/issues
Platform: UNKNOWN
Classifier: Programming Language :: Python :: 3
Classifier: License :: OSI Approved :: MIT License
Classifier: Operating System :: OS Independent
Requires-Python: >=3.6
